Metadata-Version: 2.1
Name: pyifx
Version: 1.0.3
Summary: An image handling, processing, & editing library for Python.
Home-page: https://github.com/Video-Lab/pyifx/
Author: Jad Khalili
Author-email: jad.khalili123@gmail.com
License: UNKNOWN
Platform: UNKNOWN
Classifier: Programming Language :: Python :: 3
Classifier: License :: OSI Approved :: MIT License
Classifier: Operating System :: OS Independent
